pweb_extra/__init__.py
pweb_extra/barqr/__init__.py
pweb_extra/barqr/barcode_generator.py
pweb_extra/document/__init__.py
pweb_extra/document/pweb_pdf.py
pweb_extra/pws/__init__.py
pweb_extra/pws/pweb_socket.py
pweb_extra/pws/pweb_socket_conf.py
pweb_extra-1.0.3.dist-info/LICENSE
pweb_extra-1.0.3.dist-info/METADATA
pweb_extra-1.0.3.dist-info/WHEEL
pweb_extra-1.0.3.dist-info/top_level.txt
pweb_extra-1.0.3.dist-info/RECORD
