Metadata-Version: 2.1
Name: pweb-extra
Version: 1.0.3
Summary: PWeb Extra help to email, task scheduling and various external operation.
Home-page: https://github.com/banglafighter/pweb-extra
Author: Problem Fighter
Author-email: banglafighter.com@gmail.com
License: Apache 2.0
Platform: any
Classifier: Intended Audience :: Developers
Classifier: License :: OSI Approved :: Apache Software License
Classifier: Programming Language :: Python
License-File: LICENSE
Requires-Dist: python-barcode ==0.15.1
Requires-Dist: Flask-SocketIO ==5.3.6
Requires-Dist: weasyprint ==52.5
Requires-Dist: ppy-common
Requires-Dist: ppy-file-text
